gitreco/__init__.py
gitreco/cli.py
gitreco-0.1.2.dist-info/METADATA
gitreco-0.1.2.dist-info/WHEEL
gitreco-0.1.2.dist-info/entry_points.txt
gitreco-0.1.2.dist-info/top_level.txt
gitreco-0.1.2.dist-info/RECORD
